linkedin_user_scraper/__init__.py
linkedin_user_scraper/company.py
linkedin_user_scraper/functions.py
linkedin_user_scraper/objects.py
linkedin_user_scraper/person.py
linkedin_user_scraper/scraper.py
linkedin_user_scraper-2.0.0.dist-info/DESCRIPTION.rst
linkedin_user_scraper-2.0.0.dist-info/METADATA
linkedin_user_scraper-2.0.0.dist-info/RECORD
linkedin_user_scraper-2.0.0.dist-info/WHEEL
linkedin_user_scraper-2.0.0.dist-info/metadata.json
linkedin_user_scraper-2.0.0.dist-info/top_level.txt
