Metadata-Version: 2.0
Name: linkedin-user-scraper
Version: 2.0.0
Summary: Scrapes user data from Linkedin
Home-page: https://github.com/joeyism/linkedin_user_scraper
Author: Joey Sham
Author-email: sham.joey@gmail.com
License: UNKNOWN
Download-URL: https://github.com/joeyism/linkedin_user_scraper/dist/2.0.0.tar.gz
Keywords: linkedin,scraping,scraper
Platform: UNKNOWN
Requires-Dist: lxml
Requires-Dist: request
Requires-Dist: selenium
